pystation/__init__.py
pystation/__main__.py
pystation/station.py
pystation/cli/__init__.py
pystation/cli/cli.py
pystation/funcs/__init__.py
pystation/funcs/currency.py
pystation/gui/__init__.py
pystation/gui/station_gui.py
pystation/search/__init__.py
pystation/search/highest_price.py
pystation/search/search_funcs.py
pystation/tests/__init__.py
pystation/tests/manual_testing.py
pystation/tests/test_station.py
PyPlayStation-0.0.1.dist-info/LICENSE
PyPlayStation-0.0.1.dist-info/METADATA
PyPlayStation-0.0.1.dist-info/WHEEL
PyPlayStation-0.0.1.dist-info/entry_points.txt
PyPlayStation-0.0.1.dist-info/top_level.txt
PyPlayStation-0.0.1.dist-info/RECORD
