Metadata-Version: 2.1
Name: PyPlayStation
Version: 0.0.1
Summary: Playstation Store price crawler
Author: Paavo Westerlund
License: MIT
Project-URL: Homepage, https://github.com/paavoto7/PyStation
Keywords: Playstation,Store,game price
Classifier: Development Status :: 2 - Pre-Alpha
Classifier: Programming Language :: Python :: 3
Requires-Python: >=3.8
License-File: LICENSE
Requires-Dist: beautifulsoup4 (>=4.11.1)
Requires-Dist: Pillow (>=9.2.0)
Requires-Dist: requests (>=2.28.1)
Requires-Dist: tabulate (>=0.8.10)
Provides-Extra: dev
Requires-Dist: black (>=22.6.0) ; extra == 'dev'
Requires-Dist: pytest (>=7.1.2) ; extra == 'dev'
